Workbook

Sheet Resumen
A1: ANÁLISIS DE COSTES - OMERIX ERP
A3: Fecha de análisis: | B3: Diciembre 2025
A4: Moneda: | B4: EUR (€)
A6: Concepto | B6: Mínimo (€/mes) | C6: Máximo (€/mes) | D6: Notas
A7: Hosting VPS | B7: 12.99 | C7: =Hosting!C8 -> 24.99 | D7: Hostinger KVM recomendado
A8: MongoDB Atlas | B8: 56.94 | C8: =MongoDB!C10 -> 150 | D8: M0 gratis, M20 máximo para producción
A9: API Claude (IA) | B9: ='API Claude'!E21 -> 1.794 | C9: ='API Claude'!F21 -> 3.588 | D9: Coste por procesamiento albaranes
A10: Almacenamiento (S3/DO) | B10: =Almacenamiento!B19 -> 0 | C10: =Almacenamiento!C19 -> 40 | D10: Para archivos y backups
A11: Dominio + SSL | B11: 1 | C11: 2 | D11: Renovación anual prorrateada
A12: Backup extra | B12: 0 | C12: 5 | D12: Opcional según proveedor
A13: TOTAL INFRAESTRUCTURA | B13: =SUM(B7:B12) -> 72.724 | C13: =SUM(C7:C12) -> 225.578

Sheet Hosting
A1: HOSTING VPS - COMPARATIVA
A3: Proveedor / Plan | B3: Precio (€/mes) | C3: Specs | D3: Notas
A4: Hostinger KVM1 | B4: 6 | C4: 1 vCPU, 4GB RAM | D4: Básico para desarrollo
A5: Hostinger KVM2 ⭐ | B5: =17.99+6 -> 23.99 | C5: 2 vCPU, 8GB RAM | D5: RECOMENDADO para producción
A6: Hostinger KVM4 | B6: 24.99 | C6: 4 vCPU, 16GB RAM | D6: Para múltiples clientes
A7: DigitalOcean Droplet | B7: 12 | C7: 2 vCPU, 4GB RAM | D7: Alternativa premium
A8: Rango recomendado: | B8: =MIN(B4:B7) -> 6 | C8: =MAX(B4:B7) -> 24.99 | D8: Fácil deploy, puede escalar

Sheet MongoDB
A1: MONGODB ATLAS - PLANES
A3: Plan | B3: Precio (€/mes) | C3: Almacen. | D3: Notas
A4: M0 (Free) | B4: 0 | C4: 512 MB | D4: Desarrollo/testing, sin SLA
A5: M2 (Shared) | B5: 9 | C5: 2 GB | D5: Pequeños proyectos
A6: M5 (Shared) ⭐ | B6: 30 | C6: 5 GB | D6: RECOMENDADO producción básica
A7: M10 (Dedicated) | B7: 60 | C7: 10 GB | D7: Alta disponibilidad
A8: M20 (Dedicated) | B8: 150 | C8: 20 GB | D8: Múltiples clientes
A10: Rango típico: | B10: 0 | C10: 150

Sheet API Claude
A1: COSTES API CLAUDE - PROCESAMIENTO ALBARANES
A3: Modelo: Claude Sonnet 4.5
A4: Precio entrada: $3 / millón tokens
A5: Precio salida: $15 / millón tokens
A6: Descuento Batch API: 50%
A8: Parámetro | B8: Valor | C8: Unidad
A9: Tokens entrada por albarán | B9: 2500 | C9: tokens
A10: Tokens salida por albarán | B10: 800 | C10: tokens
A11: Tipo cambio EUR/USD | B11: 0.92
A13: Coste por albarán (€): | B13: =((B9/1000000)*3 + (B10/1000000)*15)*B11 -> 0.01794
A15: Escenario | B15: Albaranes/mes | C15: Coste (€) | D15: Con Batch -50% | E15: Mínimo | F15: Máximo
A16: Autónomo | B16: 50 | C16: =B16*$B$13 -> 0.897 | D16: =C16*0.5 -> 0.4485 | E16: =D16 -> 0.4485 | F16: =C16 -> 0.897
A17: Pequeño negocio | B17: 200 | C17: =B17*$B$13 -> 3.588 | D17: =C17*0.5 -> 1.794 | E17: =D17 -> 1.794 | F17: =C17 -> 3.588
A18: Mediano | B18: 500 | C18: =B18*$B$13 -> 8.97 | D18: =C18*0.5 -> 4.485 | E18: =D18 -> 4.485 | F18: =C18 -> 8.97
A19: Grande | B19: 1000 | C19: =B19*$B$13 -> 17.94 | D19: =C19*0.5 -> 8.97 | E19: =D19 -> 8.97 | F19: =C19 -> 17.94
A20: Enterprise | B20: 3000 | C20: =B20*$B$13 -> 53.82 | D20: =C20*0.5 -> 26.91 | E20: =D20 -> 26.91 | F20: =C20 -> 53.82
A21: Rango típico (pequeño): | E21: =E17 -> 1.794 | F21: =F17 -> 3.588

Sheet Almacenamiento
A1: ALMACENAMIENTO - DIGITALOCEAN SPACES vs AWS S3
A3: 📦 DIGITALOCEAN SPACES
A4: Concepto | B4: Precio | C4: Incluido | D4: Notas
A5: Plan base | B5: $5/mes | C5: 250 GB + 1 TB transfer | D5: CDN incluido gratis
A6: Almacenamiento extra | B6: $0.02/GiB | C6: - | D6: Sobre los 250 GB
A7: Transferencia extra | B7: $0.01/GiB | C7: - | D7: Sobre 1 TB salida
A8: Inbound (entrada) | B8: GRATIS | C8: Ilimitado | D8: Subir archivos sin coste
A10: ☁️ AWS S3
A11: Clase de almacenamiento | B11: Precio/GB/mes | C11: Uso recomendado | D11: Notas
A12: S3 Standard | B12: $0.023 | C12: Acceso frecuente | D12: Primeros 50 TB
A13: S3 Standard-IA | B13: $0.0125 | C13: Acceso infrecuente | D13: Recuperación rápida
A14: S3 One Zone-IA | B14: $0.01 | C14: Backups secundarios | D14: Sin redundancia multi-zona
A15: S3 Glacier Instant | B15: $0.004 | C15: Archivo con acceso rápido | D15: 68% más barato que IA
A16: Transfer OUT | B16: $0.09/GB | C16: Descarga a internet | D16: Primeros 10 TB
A18: ⭐ RECOMENDACIÓN PARA OMERIX
A19: Rango mensual estimado: | B19: 0 | C19: 40 | D19: Uso típico: 50-100 GB
A21: Para un ERP como Omerix con almacenamiento de:
A22: • Imágenes de albaranes/facturas
A23: • Backups de MongoDB
A24: • Archivos de clientes
A26: ✅ RECOMENDACIÓN: DigitalOcean Spaces
A27: Razones:
A28: 1. Precio fijo predecible ($5/mes incluye 250 GB)
A29: 2. CDN integrado sin coste extra
A30: 3. Compatible S3 (fácil migración)
A31: 4. Transfer generoso (1 TB incluido)
A32: 5. Simplicidad vs complejidad de precios AWS
A34: 📊 CALCULADORA DE COSTES
A35: Tu escenario | B35: Valor | C35: DO Spaces | D35: AWS S3
A36: GB almacenados | B36: 2048 | C36: =IF(B36<=250,5,5+(B36-250)*0.02) -> 40.96 | D36: =B36*0.023 -> 47.104
A37: GB transfer salida/mes | B37: 50 | C37: =IF(B37<=1024,0,(B37-1024)*0.01) -> 0 | D37: =B37*0.09 -> 4.5
A38: TOTAL MENSUAL (€) | C38: =(C36+C37)*0.92 -> 37.6832 | D38: =(D36+D37)*0.92 -> 47.47568

Sheet Precios SaaS
A1: MODELO DE PRECIOS SAAS - OMERIX
A3: Plan | B3: Usuarios | C3: Precio (€/mes) | D3: Características
A4: Starter | B4: 1-2 | C4: 29 | D4: Módulos básicos, 1 empresa
A5: Profesional | B5: 3-5 | C5: 59 | D5: + Informes avanzados, soporte email
A6: Business | B6: 6-10 | C6: 99 | D6: + Multi-empresa, API, prioridad
A7: Enterprise | B7: Ilimitados | C7: 199 | D7: + Personalización, SLA, soporte 24/7
A10: 💡 MÓDULO IA (Pay-per-use)
A11: Volumen docs/mes | B11: Precio/doc (€) | C11: Tu coste | D11: Tu margen
A12: 1-50 | B12: 0.3 | C12: =0.015 -> 0.015 | D12: =1-(C12/B12) -> 0.95
A13: 51-200 | B13: 0.25 | C13: =0.015 -> 0.015 | D13: =1-(C13/B13) -> 0.94
A14: 201-500 | B14: 0.2 | C14: =0.015 -> 0.015 | D14: =1-(C14/B14) -> 0.925
A15: 501-1000 | B15: 0.15 | C15: =0.015 -> 0.015 | D15: =1-(C15/B15) -> 0.9
A16: +1000 | B16: 0.12 | C16: =0.015 -> 0.015 | D16: =1-(C16/B16) -> 0.875
A19: 📈 ANÁLISIS ROI
A20: Inversión desarrollo (estimada): | B20: 8000 | C20: €
A21: Clientes plan Profesional: | B21: 10
A22: Ingresos mensuales: | B22: =B21*59 -> 590
A23: Costes mensuales infra: | B23: =Resumen!C13 -> 225.578
A24: Beneficio mensual: | B24: =B22-B23 -> 364.422
A25: Meses para break-even: | B25: =ROUND(B20/B24,1) -> 22
